README.rst
setup.py
AnechoDB_Access.egg-info/PKG-INFO
AnechoDB_Access.egg-info/SOURCES.txt
AnechoDB_Access.egg-info/dependency_links.txt
AnechoDB_Access.egg-info/requires.txt
AnechoDB_Access.egg-info/top_level.txt
share_belen/__init__.py
share_belen/computation.py
share_belen/connection.py