Metadata-Version: 1.1
Name: AnechoDB-Access
Version: 1.0
Summary: A library to comunicate with the database Belen to search, download and compute beam stored in it
Home-page: https://github.com/JacopoMartelli/AnechoDB_Access
Author: Jacopo Martelli
Author-email: martelli.jacopo@gmail.com
License: MIT
Platform: UNKNOWN
Requires: Python (>3.3)
